ncellapp/NcellApp.py
ncellapp/__init__.py
ncellapp/models.py
ncellapp/ncell.py
ncellapp/register.py
ncellapp/signatures.py
ncellapp-2.0.2.dist-info/licenses/LICENSE
ncellapp-2.0.2.dist-info/METADATA
ncellapp-2.0.2.dist-info/WHEEL
ncellapp-2.0.2.dist-info/top_level.txt
ncellapp-2.0.2.dist-info/RECORD
