Metadata-Version: 2.4
Name: ncellapp
Version: 2.0.2
Summary: Unofficial Python API Wrapper of Ncell
Home-page: https://github.com/hemantapkh/ncellapp
Author: Hemanta Pokharel
Author-email: yo@hemantapkh.com
Project-URL: Documentation, https://ncellapp.readthedocs.io/en/latest/
Project-URL: Issue tracker, https://github.com/hemantapkh/ncellapp/issues
Classifier: Development Status :: 4 - Beta
Classifier: Intended Audience :: Developers
Classifier: Programming Language :: Python :: 3
Classifier: License :: OSI Approved :: MIT License
Classifier: Operating System :: OS Independent
Classifier: Topic :: Internet
Classifier: Topic :: Software Development :: Libraries
Classifier: Topic :: Software Development :: Libraries :: Python Modules
Classifier: Topic :: Utilities
Requires-Python: >=3.0
License-File: LICENSE
Requires-Dist: requests
Requires-Dist: emoji
Dynamic: author
Dynamic: author-email
Dynamic: classifier
Dynamic: description
Dynamic: description-content-type
Dynamic: home-page
Dynamic: license-file
Dynamic: project-url
Dynamic: requires-dist
Dynamic: requires-python
Dynamic: summary
